realtime_operator/__init__.py
realtime_operator/alignment.py
realtime_operator/compression.py
realtime_operator/single_operator.py
realtime_operator-0.3.3.dist-info/LICENSE
realtime_operator-0.3.3.dist-info/METADATA
realtime_operator-0.3.3.dist-info/WHEEL
realtime_operator-0.3.3.dist-info/top_level.txt
realtime_operator-0.3.3.dist-info/RECORD
