Metadata-Version: 2.1
Name: realtime_operator
Version: 0.3.3
Summary: A package to perfom real-time operations on time series data streams.
Author-email: Ernst Holger Amort <holgeramort@gmail.com>
Project-URL: Homepage, https://github.com/ErnstHolger/realtime_operator
Project-URL: Issues, https://github.com/ErnstHolger/realtime_operator/issues
Classifier: Programming Language :: Python :: 3
Classifier: License :: OSI Approved :: MIT License
Classifier: Operating System :: OS Independent
Requires-Python: >=3.10
License-File: LICENSE
Requires-Dist: numba
Requires-Dist: numpy
Requires-Dist: pytest
Requires-Dist: python-dateutil
